whodidwhat/__init__.py
whodidwhat/common_paths.py
whodidwhat/path_functions.py
whodidwhat/statistics.py
whodidwhat/svnfilter.py
whodidwhat-0.0.5.dist-info/DESCRIPTION.rst
whodidwhat-0.0.5.dist-info/METADATA
whodidwhat-0.0.5.dist-info/RECORD
whodidwhat-0.0.5.dist-info/WHEEL
whodidwhat-0.0.5.dist-info/entry_points.txt
whodidwhat-0.0.5.dist-info/metadata.json
whodidwhat-0.0.5.dist-info/top_level.txt
