Metadata-Version: 2.0
Name: whodidwhat
Version: 0.0.5
Summary: Package for filtering vcs repositories
Home-page: https://github.com/jkohvakk/whodidwhat
Author: Janne Kohvakka
Author-email: jkohvakk@gmail.com
License: MIT
Keywords: git svn blame filter
Platform: UNKNOWN
Classifier: Development Status :: 3 - Alpha
Classifier: Intended Audience :: Developers
Classifier: Topic :: Software Development :: Version Control
Classifier: License :: OSI Approved :: MIT License
Classifier: Programming Language :: Python :: 2.7
Requires-Dist: mock
Provides-Extra: test
Requires-Dist: pytest; extra == 'test'
